Metadata-Version: 1.0
Name: Recopytex
Version: 1.1.1
Summary: Assessment analysis
Home-page: UNKNOWN
Author: Benjamin Bertrand
Author-email: UNKNOWN
License: UNKNOWN
Platform: UNKNOWN
